litellm_kamiwaza/__init__.py
litellm_kamiwaza/kamiwaza_router.py
litellm_kamiwaza/version.py
litellm_kamiwaza-0.1.4.dist-info/licenses/LICENSE
tests/__init__.py
tests/conftest.py
tests/static_models_conf.py
tests/test_kamiwaza_router.py
litellm_kamiwaza-0.1.4.dist-info/METADATA
litellm_kamiwaza-0.1.4.dist-info/WHEEL
litellm_kamiwaza-0.1.4.dist-info/top_level.txt
litellm_kamiwaza-0.1.4.dist-info/RECORD
