Metadata-Version: 2.4
Name: litellm-kamiwaza
Version: 0.1.4
Summary: LiteLLM Router integration for Kamiwaza AI
Author-email: Matt Wallace <matt@kamiwaza.ai>
License: MIT
Project-URL: Homepage, https://github.com/kamiwaza-ai/litellm-kamiwaza
Project-URL: Bug Tracker, https://github.com/kamiwaza-ai/litellm-kamiwaza/issues
Classifier: Programming Language :: Python :: 3
Classifier: License :: OSI Approved :: MIT License
Classifier: Operating System :: OS Independent
License-File: LICENSE
Requires-Dist: litellm>=1.6.7
Requires-Dist: kamiwaza>=0.3.3.0
Dynamic: license-file
